nb_offline_convert/__init__.py
nb_offline_convert/offline_HTML.py
nb_offline_convert/offline_WebPDF.py
nb_offline_convert/tools.py
nb_offline_convert-0.1.1.data/data/share/jupyter/nbconvert/templates/lab_offline/conf.json
nb_offline_convert-0.1.1.data/data/share/jupyter/nbconvert/templates/lab_offline/index.html.j2
nb_offline_convert-0.1.1.data/data/share/jupyter/nbconvert/templates/lab_offline/static/require.min.js
nb_offline_convert-0.1.1.data/data/share/jupyter/nbconvert/templates/lab_offline/static/@jupyter-widgets/html-manager@0.20.0/dist/674f50d287a8c48dc19ba404d20fe713.eot
nb_offline_convert-0.1.1.data/data/share/jupyter/nbconvert/templates/lab_offline/static/@jupyter-widgets/html-manager@0.20.0/dist/912ec66d7572ff821749319396470bde.svg
nb_offline_convert-0.1.1.data/data/share/jupyter/nbconvert/templates/lab_offline/static/@jupyter-widgets/html-manager@0.20.0/dist/af7ae505a9eed503f8b8e6982036873e.woff2
nb_offline_convert-0.1.1.data/data/share/jupyter/nbconvert/templates/lab_offline/static/@jupyter-widgets/html-manager@0.20.0/dist/b06871f281fee6b241d60582ae9369b9.ttf
nb_offline_convert-0.1.1.data/data/share/jupyter/nbconvert/templates/lab_offline/static/@jupyter-widgets/html-manager@0.20.0/dist/embed-amd.js
nb_offline_convert-0.1.1.data/data/share/jupyter/nbconvert/templates/lab_offline/static/@jupyter-widgets/html-manager@0.20.0/dist/fee66e712a8a08eef5805a46892932ad.woff
nb_offline_convert-0.1.1.data/data/share/jupyter/nbconvert/templates/lab_offline/static/MathJax/LICENSE
nb_offline_convert-0.1.1.data/data/share/jupyter/nbconvert/templates/lab_offline/static/MathJax/MathJax.js
nb_offline_convert-0.1.1.data/data/share/jupyter/nbconvert/templates/lab_offline/static/MathJax/README.md
nb_offline_convert-0.1.1.data/data/share/jupyter/nbconvert/templates/lab_offline/static/MathJax/config/Safe.js
nb_offline_convert-0.1.1.data/data/share/jupyter/nbconvert/templates/lab_offline/static/MathJax/config/TeX-AMS-MML_HTMLorMML-full.js
nb_offline_convert-0.1.1.dist-info/LICENSE.md
nb_offline_convert-0.1.1.dist-info/METADATA
nb_offline_convert-0.1.1.dist-info/WHEEL
nb_offline_convert-0.1.1.dist-info/entry_points.txt
nb_offline_convert-0.1.1.dist-info/top_level.txt
nb_offline_convert-0.1.1.dist-info/RECORD
