Metadata-Version: 2.1
Name: nb-offline-convert
Version: 0.1.1
Summary: An offline exporter for nbconvert.
Home-page: https://github.com/trungleduc/nb_offline_convert
Author: Duc Trung Le
Author-email: leductrungxf@gmail.com
License: MIT
Keywords: jupyter,notebook,nbconvert
Platform: UNKNOWN
Classifier: Development Status :: 3 - Alpha
Classifier: Intended Audience :: End Users/Desktop
Classifier: Intended Audience :: Developers
Classifier: Intended Audience :: Science/Research
Classifier: License :: OSI Approved :: MIT License
Classifier: Natural Language :: English
Classifier: Programming Language :: Python :: 3
Classifier: Programming Language :: Python :: 3.6
Classifier: Programming Language :: Python :: 3.7
Classifier: Programming Language :: Python :: 3.8
Classifier: Programming Language :: Python :: 3.9
Requires-Python: >=3.6
License-File: LICENSE.md
Requires-Dist: nbconvert
